admin_action_tools/__init__.py
admin_action_tools/admin/__init__.py
admin_action_tools/admin/base.py
admin_action_tools/admin/confirm_tool.py
admin_action_tools/admin/form_tool.py
admin_action_tools/constants.py
admin_action_tools/file_cache.py
admin_action_tools/static/admin/css/confirmation.css
admin_action_tools/templates/admin/confirm_tool/action_confirmation.html
admin_action_tools/templates/admin/confirm_tool/change_confirmation.html
admin_action_tools/templates/admin/form_tool/action_form.html
admin_action_tools/templates/admin/submit_line.html
admin_action_tools/templates/include/change_data.html
admin_action_tools/templates/include/form.html
admin_action_tools/templates/include/submit_row.html
admin_action_tools/templatetags/__init__.py
admin_action_tools/templatetags/formatting.py
admin_action_tools/tests/helpers.py
admin_action_tools/tests/integration/confirm-tool/test_with_cache.py
admin_action_tools/tests/integration/confirm-tool/test_with_change_actions.py
admin_action_tools/tests/integration/confirm-tool/test_with_form_input_types.py
admin_action_tools/tests/integration/confirm-tool/test_with_inlines.py
admin_action_tools/tests/integration/confirm-tool/test_with_s3_storage.py
admin_action_tools/tests/integration/confirm-tool/test_with_validators_integration.py
admin_action_tools/tests/integration/form-tool/test_with_form_actions.py
admin_action_tools/tests/integration/form-tool/test_with_multiple_forms.py
admin_action_tools/tests/integration/test_smoke.py
admin_action_tools/tests/snapshot/screenshot.png
admin_action_tools/tests/unit/confirm-tool/test_admin_options.py
admin_action_tools/tests/unit/confirm-tool/test_confirm_actions.py
admin_action_tools/tests/unit/confirm-tool/test_confirm_change_and_add.py
admin_action_tools/tests/unit/confirm-tool/test_confirm_change_and_add_m2m_field.py
admin_action_tools/tests/unit/confirm-tool/test_confirm_save_actions.py
admin_action_tools/tests/unit/confirm-tool/test_confirmation_cache.py
django_admin_action_tools-1.3.1.dist-info/METADATA
django_admin_action_tools-1.3.1.dist-info/WHEEL
django_admin_action_tools-1.3.1.dist-info/licenses/LICENSE
django_admin_action_tools-1.3.1.dist-info/RECORD
