Metadata-Version: 2.4
Name: django-admin-action-tools
Version: 1.3.1
Summary: Tools for django admin
License: Apache-2.0
License-File: LICENSE
Author: Thu Trang Pham
Author-email: thuutrangpham@gmail.com
Maintainer: jeanloup.monnier
Maintainer-email: jean-loup.monnier@spikeelabs.fr
Requires-Python: >=3.10,<4.0
Classifier: Framework :: Django :: 4.2
Classifier: Framework :: Django :: 5.2
Classifier: License :: OSI Approved :: Apache Software License
Classifier: Programming Language :: Python :: 3
Classifier: Programming Language :: Python :: 3.10
Classifier: Programming Language :: Python :: 3.11
Classifier: Programming Language :: Python :: 3.12
Classifier: Programming Language :: Python :: 3.13
Classifier: Programming Language :: Python :: 3.14
Classifier: Programming Language :: Python :: 3 :: Only
Requires-Dist: Django (>=4.2)
Requires-Dist: django-widget-tweaks (>=1.4,<2.0)
Project-URL: Repository, https://github.com/SpikeeLabs/django-admin-action-tools
